.gitignore
LICENCE
Makefile
README.md
setup.cfg
setup.py
.github/FUNDING.yml
.github/workflows/main.yml
airspeed/__init__.py
airspeed/api.py
airspeed/operators.py
airspeed_ext.egg-info/PKG-INFO
airspeed_ext.egg-info/SOURCES.txt
airspeed_ext.egg-info/dependency_links.txt
airspeed_ext.egg-info/entry_points.txt
airspeed_ext.egg-info/requires.txt
airspeed_ext.egg-info/top_level.txt
airspeed_ext.egg-info/zip-safe
tests/__init__.py
tests/conftest.py
tests/test_templating.py
tests/test_templating.snapshot.json